pysapcompress.pyd
pysap/SAPCAR.py
pysap/SAPCredv2.py
pysap/SAPDiag.py
pysap/SAPDiagClient.py
pysap/SAPDiagItems.py
pysap/SAPEnqueue.py
pysap/SAPHDB.py
pysap/SAPIGS.py
pysap/SAPLPS.py
pysap/SAPMS.py
pysap/SAPNI.py
pysap/SAPPSE.py
pysap/SAPRFC.py
pysap/SAPRouter.py
pysap/SAPSNC.py
pysap/SAPSSFS.py
pysap/__init__.py
pysap/utils/__init__.py
pysap/utils/console.py
pysap/utils/fields.py
pysap/utils/crypto/__init__.py
pysap/utils/crypto/rsec.py
pysap-0.1.19.data/scripts/pysapcar
pysap-0.1.19.data/scripts/pysapgenpse
pysap-0.1.19.dist-info/COPYING
pysap-0.1.19.dist-info/METADATA
pysap-0.1.19.dist-info/WHEEL
pysap-0.1.19.dist-info/top_level.txt
pysap-0.1.19.dist-info/RECORD
