Metadata-Version: 2.1
Name: pysap
Version: 0.1.19
Summary: Python library for crafting SAP's network protocols packets
Home-page: https://www.secureauth.com/labs/open-source-tools/pysap
Author: Martin Gallo
Author-email: mgallo@secureauth.com
License: GNU General Public License v2 or later (GPLv2+)
Download-URL: https://www.secureauth.com/labs/open-source-tools/pysap
Platform: UNKNOWN
Classifier: Development Status :: 3 - Alpha
Classifier: Intended Audience :: Developers
Classifier: Intended Audience :: Information Technology
Classifier: Intended Audience :: System Administrators
Classifier: License :: OSI Approved :: GNU General Public License v2 or later (GPLv2+)
Classifier: Programming Language :: Python
Classifier: Programming Language :: C++
Classifier: Topic :: Security
Provides: pysapcompress
Provides: pysap
Requires-Dist: scapy (==2.4.4)
Requires-Dist: cryptography (==2.9.2)
Provides-Extra: docs
Requires-Dist: Sphinx (==1.8.5) ; extra == 'docs'
Requires-Dist: ipykernel ; extra == 'docs'
Requires-Dist: nbsphinx (==0.5.1) ; extra == 'docs'
Requires-Dist: pyx (==0.12.1) ; extra == 'docs'
Requires-Dist: ipython (<6.0) ; extra == 'docs'
Requires-Dist: m2r (==0.2.1) ; extra == 'docs'
Provides-Extra: examples
Requires-Dist: tabulate (==0.8.9) ; extra == 'examples'
Requires-Dist: netaddr (==0.8.0) ; extra == 'examples'
Requires-Dist: PyJWT (==1.7.1) ; extra == 'examples'
Requires-Dist: requests ; extra == 'examples'
